speed/__init__.py
execspeed-0.1.0.dist-info/LICENSE.txt
execspeed-0.1.0.dist-info/METADATA
execspeed-0.1.0.dist-info/WHEEL
execspeed-0.1.0.dist-info/top_level.txt
execspeed-0.1.0.dist-info/RECORD
