Metadata-Version: 2.1
Name: execspeed
Version: 0.1.0
Summary: Simple tool for finding average function execution time
Home-page: https://github.com/Astrochamp/speed
Author: Ivan O'Connor
Author-email: ivanoconnor@hotmail.co.uk
License: UNKNOWN
Project-URL: Bug Tracker, https://github.com/Astrochamp/speed/issues
Platform: UNKNOWN
Classifier: Programming Language :: Python :: 3
Classifier: License :: OSI Approved :: MIT License
Classifier: Operating System :: OS Independent
Requires-Python: >=3.6
License-File: LICENSE.txt
